{
    "W": 200,
    "H": 200,
    "depth": 1.0,
    "height": 10.0,
    "num_of_relays": 100,
    "num_of_sensors": 100,
    "relays": [
        {
            "x": 58.32130161627433,
            "y": 38.815288096483044,
            "z": 10.0
        },
        {
            "x": 83.40057342441659,
            "y": 55.867620358825924,
            "z": 22.013981602177424
        },
        {
            "x": 71.75451256489367,
            "y": 57.6824323241269,
            "z": 19.33687080482748
        },
        {
            "x": 43.8166650343631,
            "y": 64.8843031607646,
            "z": 10.0
        },
        {
            "x": 67.30734215604467,
            "y": 64.53133052296397,
            "z": 17.250128836742352
        },
        {
            "x": 50.36881013450034,
            "y": 50.3562765148393,
            "z": 10.0
        },
        {
            "x": 63.24739508471976,
            "y": 67.42331311643255,
            "z": 10.0
        },
        {
            "x": 76.4030499845826,
            "y": 42.54970088061791,
            "z": 21.37800311603949
        },
        {
            "x": 65.5291366465589,
            "y": 70.85344505174348,
            "z": 10.664692479286709
        },
        {
            "x": 55.036768719208,
            "y": 36.81470937843538,
            "z": 10.0
        },
        {
            "x": 58.26307760988158,
            "y": 59.205382265095345,
            "z": 10.0
        },
        {
            "x": 89.64096671026336,
            "y": 40.60838531154247,
            "z": 21.72732494876669
        },
        {
            "x": 86.55735168360022,
            "y": 50.38753565539439,
            "z": 25.978677017345994
        },
        {
            "x": 58.876080951423425,
            "y": 31.752125133596195,
            "z": 10.0
        },
        {
            "x": 83.79977527073575,
            "y": 67.61262845524854,
            "z": 24.521435829556555
        },
        {
            "x": 54.012377019270616,
            "y": 69.33148632437626,
            "z": 10.0
        },
        {
            "x": 46.23928800839234,
            "y": 49.689222833656466,
            "z": 10.0
        },
        {
            "x": 83.23550051748832,
            "y": 40.84851801771766,
            "z": 22.686946298842567
        },
        {
            "x": 53.56684148132913,
            "y": 68.4060088610315,
            "z": 10.0
        },
        {
            "x": 61.256618844250774,
            "y": 58.01364890644347,
            "z": 10.0
        },
        {
            "x": 84.19871024800233,
            "y": 77.0884054691605,
            "z": 22.248663419560042
        },
        {
            "x": 49.10613974399007,
            "y": 41.83997479019003,
            "z": 10.0
        },
        {
            "x": 63.37519406080066,
            "y": 49.383617595835375,
            "z": 10.0
        },
        {
            "x": 74.66281599095393,
            "y": 72.17407647908412,
            "z": 15.27083583382095
        },
        {
            "x": 72.16310198265793,
            "y": 73.89080496556497,
            "z": 17.899697244740416
        },
        {
            "x": 57.901399582511125,
            "y": 55.2085222306649,
            "z": 10.0
        },
        {
            "x": 69.23535912362217,
            "y": 35.857183209877576,
            "z": 14.786239757512254
        },
        {
            "x": 59.759461305348324,
            "y": 56.047921675572624,
            "z": 10.0
        },
        {
            "x": 72.86931237221891,
            "y": 30.959496647724876,
            "z": 17.699812360549387
        },
        {
            "x": 64.08078135349695,
            "y": 49.070641754044466,
            "z": 10.0
        },
        {
            "x": 68.19593668740116,
            "y": 30.70092133061469,
            "z": 15.641181194765645
        },
        {
            "x": 68.71566261640618,
            "y": 79.22198101089083,
            "z": 11.905690326160745
        },
        {
            "x": 77.18272090158607,
            "y": 31.637561321922362,
            "z": 20.252422005518547
        },
        {
            "x": 79.56511965118072,
            "y": 72.99798650505069,
            "z": 19.868442809192373
        },
        {
            "x": 67.66835807307427,
            "y": 80.07423941014301,
            "z": 10.013847977705574
        },
        {
            "x": 69.89629357732315,
            "y": 71.43076222991566,
            "z": 10.864392507252022
        },
        {
            "x": 59.14982534106107,
            "y": 62.216411942282505,
            "z": 10.0
        },
        {
            "x": 58.61644185166826,
            "y": 63.541184734574315,
            "z": 10.0
        },
        {
            "x": 57.50151785578622,
            "y": 48.19235251414107,
            "z": 10.0
        },
        {
            "x": 70.485558621817,
            "y": 73.90565472258854,
            "z": 18.513816969767117
        },
        {
            "x": 67.40498823102035,
            "y": 28.857843220912855,
            "z": 17.18746805431502
        },
        {
            "x": 61.87229373724424,
            "y": 56.96250169948063,
            "z": 10.0
        },
        {
            "x": 68.75980355732551,
            "y": 63.92534171850534,
            "z": 16.28054674960854
        },
        {
            "x": 78.68649237584623,
            "y": 55.887823200053155,
            "z": 22.043352152233744
        },
        {
            "x": 85.05049271946956,
            "y": 53.139045201856014,
            "z": 33.48805235056534
        },
        {
            "x": 50.07396960600286,
            "y": 40.204372361575466,
            "z": 10.0
        },
        {
            "x": 81.04896261325666,
            "y": 69.46598016786055,
            "z": 25.925149158952884
        },
        {
            "x": 57.56436375435472,
            "y": 56.802803357764176,
            "z": 10.0
        },
        {
            "x": 70.18135539872941,
            "y": 52.78891620446948,
            "z": 17.598246041716653
        },
        {
            "x": 56.7796584734252,
            "y": 70.98418562842933,
            "z": 10.0
        },
        {
            "x": 61.60646613839025,
            "y": 79.61701482443871,
            "z": 10.0
        },
        {
            "x": 78.19558001919584,
            "y": 43.04954299689325,
            "z": 21.5010836319264
        },
        {
            "x": 54.602741226390535,
            "y": 67.01878971937616,
            "z": 10.0
        },
        {
            "x": 67.08943691231514,
            "y": 40.14374910761267,
            "z": 12.491506506887351
        },
        {
            "x": 54.92890976748651,
            "y": 61.80764685020208,
            "z": 10.0
        },
        {
            "x": 63.71112472390939,
            "y": 75.75610752083864,
            "z": 10.0
        },
        {
            "x": 73.45235831706219,
            "y": 38.5028777511132,
            "z": 19.3585023446517
        },
        {
            "x": 57.9659593685767,
            "y": 74.73023759433602,
            "z": 10.0
        },
        {
            "x": 53.52129659974007,
            "y": 56.298962093675605,
            "z": 10.0
        },
        {
            "x": 48.93503736969009,
            "y": 54.81855204237979,
            "z": 10.0
        },
        {
            "x": 63.788969483004045,
            "y": 47.473389079873265,
            "z": 10.0
        },
        {
            "x": 63.51892891435488,
            "y": 37.24069554834632,
            "z": 11.925301614212632
        },
        {
            "x": 63.63146377785212,
            "y": 78.97593298582767,
            "z": 10.0
        },
        {
            "x": 64.79878704169494,
            "y": 68.49259096695117,
            "z": 10.0
        },
        {
            "x": 70.60233686268026,
            "y": 57.972460384341076,
            "z": 19.047177400128326
        },
        {
            "x": 72.4044786577893,
            "y": 35.1504323518856,
            "z": 17.53991911229898
        },
        {
            "x": 67.42164340691416,
            "y": 67.03018159081574,
            "z": 12.4616704070272
        },
        {
            "x": 88.2821186480066,
            "y": 56.28065347588283,
            "z": 31.234582259459696
        },
        {
            "x": 77.39417405936106,
            "y": 51.88670021819206,
            "z": 19.90900620585221
        },
        {
            "x": 61.427378368937255,
            "y": 54.794489972368524,
            "z": 10.0
        },
        {
            "x": 60.280125086831504,
            "y": 82.84642828392316,
            "z": 10.0
        },
        {
            "x": 76.05511253146787,
            "y": 77.18222648002674,
            "z": 18.860467929581503
        },
        {
            "x": 70.51813059072673,
            "y": 33.79440053002631,
            "z": 19.335494294342126
        },
        {
            "x": 62.725494622217965,
            "y": 52.65137149530066,
            "z": 10.0
        },
        {
            "x": 59.55917947670822,
            "y": 41.67937581004981,
            "z": 10.0
        },
        {
            "x": 67.77563294794368,
            "y": 45.15625438462845,
            "z": 10.2326588226761
        },
        {
            "x": 82.94498476564081,
            "y": 76.82423327393245,
            "z": 22.23523632080429
        },
        {
            "x": 80.65766104558233,
            "y": 60.32228283628685,
            "z": 21.38935847814595
        },
        {
            "x": 64.47642395068002,
            "y": 46.51335682397417,
            "z": 10.0
        },
        {
            "x": 73.6813054414569,
            "y": 69.55937973952243,
            "z": 19.804719823920607
        },
        {
            "x": 57.13628767433909,
            "y": 50.08813453271248,
            "z": 10.0
        },
        {
            "x": 75.37740958406854,
            "y": 77.31845875173101,
            "z": 19.234630184851156
        },
        {
            "x": 51.352774382858335,
            "y": 66.34899057216778,
            "z": 10.0
        },
        {
            "x": 54.28422214333486,
            "y": 61.630473928352004,
            "z": 10.0
        },
        {
            "x": 71.45611907456667,
            "y": 60.61828552897923,
            "z": 18.546261740797213
        },
        {
            "x": 50.144941245408646,
            "y": 57.88803390414368,
            "z": 10.0
        },
        {
            "x": 74.78738471948763,
            "y": 61.987665406099865,
            "z": 19.22640788669053
        },
        {
            "x": 74.90596870636725,
            "y": 78.52576948625048,
            "z": 14.160790563744282
        },
        {
            "x": 53.83755648732973,
            "y": 54.78077317677513,
            "z": 10.0
        },
        {
            "x": 57.99098812754237,
            "y": 42.568668938260444,
            "z": 10.0
        },
        {
            "x": 80.6003022296783,
            "y": 37.47929080434502,
            "z": 24.221564451135094
        },
        {
            "x": 49.89891394005175,
            "y": 34.017219419917,
            "z": 10.0
        },
        {
            "x": 72.3519510434324,
            "y": 48.67508995396219,
            "z": 18.26462778210596
        },
        {
            "x": 45.89242822746712,
            "y": 63.4817229853777,
            "z": 10.0
        },
        {
            "x": 42.159379586486914,
            "y": 62.647007879586134,
            "z": 10.0
        },
        {
            "x": 54.34230978348915,
            "y": 62.950382494923865,
            "z": 10.0
        },
        {
            "x": 66.60668465630435,
            "y": 69.67850032393288,
            "z": 16.282900568696146
        },
        {
            "x": 50.45795597936934,
            "y": 72.6046583751032,
            "z": 10.0
        },
        {
            "x": 52.58973366742021,
            "y": 76.13513476688608,
            "z": 10.0
        },
        {
            "x": 66.91236673170596,
            "y": 50.49986615586774,
            "z": 10.699812618214839
        }
    ],
    "sensors": [
        {
            "x": 61.03175677067557,
            "y": 12.061045284329182,
            "z": -1.0
        },
        {
            "x": 58.33385903413122,
            "y": 98.09872022356058,
            "z": -1.0
        },
        {
            "x": 94.28564972027208,
            "y": 19.176953584223952,
            "z": 19.829386907333195
        },
        {
            "x": 94.12067070421075,
            "y": 25.865652796420818,
            "z": 19.5887524896414
        },
        {
            "x": 73.99648043124655,
            "y": 98.19598475621223,
            "z": 5.009351220725744
        },
        {
            "x": 34.905444307736545,
            "y": 77.0431370728153,
            "z": -1.0
        },
        {
            "x": 45.77850933077862,
            "y": 74.4147534656493,
            "z": -1.0
        },
        {
            "x": 42.44544802048923,
            "y": 102.91703128379753,
            "z": -1.0
        },
        {
            "x": 94.08439846803094,
            "y": 71.18562444557313,
            "z": 39.88104428296624
        },
        {
            "x": 24.43754923157006,
            "y": 60.458243326915635,
            "z": -1.0
        },
        {
            "x": 44.679978166564894,
            "y": 18.42816047398958,
            "z": -1.0
        },
        {
            "x": 86.55982775073497,
            "y": 15.337528619396252,
            "z": 8.758942548052488
        },
        {
            "x": 90.49736222997689,
            "y": 13.381837453402852,
            "z": 11.378942559324354
        },
        {
            "x": 25.409550290642443,
            "y": 49.246981690677536,
            "z": -1.0
        },
        {
            "x": 62.87874240624084,
            "y": 12.113121473499675,
            "z": -1.0
        },
        {
            "x": 56.048571613233456,
            "y": 103.89957266490754,
            "z": -1.0
        },
        {
            "x": 34.57070322967681,
            "y": 43.447650852049605,
            "z": -1.0
        },
        {
            "x": 84.14049479883857,
            "y": 97.38548916751667,
            "z": 9.442238086002652
        },
        {
            "x": 94.19606083216767,
            "y": 101.17638094069594,
            "z": 23.264932168035326
        },
        {
            "x": 32.35253150359718,
            "y": 69.88074433249827,
            "z": -1.0
        },
        {
            "x": 61.47702447012538,
            "y": 106.33903108754862,
            "z": -1.0
        },
        {
            "x": 51.768867562004424,
            "y": 78.7446369514059,
            "z": -1.0
        },
        {
            "x": 82.86324881098206,
            "y": 101.319097704492,
            "z": 7.810590948823696
        },
        {
            "x": 73.60546876329086,
            "y": 93.78187994042705,
            "z": 6.476303915274027
        },
        {
            "x": 59.140557986186806,
            "y": 26.666059333167127,
            "z": -1.0
        },
        {
            "x": 36.148210303594595,
            "y": 73.43202915877137,
            "z": -1.0
        },
        {
            "x": 74.30095962929646,
            "y": 100.0538233496079,
            "z": -0.9216373350079529
        },
        {
            "x": 55.8590765805772,
            "y": 81.69562991284174,
            "z": -1.0
        },
        {
            "x": 93.61790983151386,
            "y": 64.11796754226862,
            "z": 54.28248301961384
        },
        {
            "x": 73.16728345016055,
            "y": 10.947670364302752,
            "z": -1.0
        },
        {
            "x": 102.8563867866974,
            "y": 45.05198465590487,
            "z": 54.18160180922119
        },
        {
            "x": 45.08042001915922,
            "y": 24.74762188122196,
            "z": -1.0
        },
        {
            "x": 34.19984324713859,
            "y": 72.1288349477172,
            "z": -1.0
        },
        {
            "x": 86.45491324984701,
            "y": 97.13944104015,
            "z": 19.490164195405672
        },
        {
            "x": 98.97792795698106,
            "y": 36.11424692824544,
            "z": 40.06492837281249
        },
        {
            "x": 70.43879491038771,
            "y": 99.84322998131934,
            "z": 9.485091185651338
        },
        {
            "x": 82.31504115726649,
            "y": 14.662940692686334,
            "z": 7.937575506490331
        },
        {
            "x": 91.24595191765412,
            "y": 28.077299879875895,
            "z": 25.825850718145702
        },
        {
            "x": 86.99766322216135,
            "y": 80.66669966022974,
            "z": 17.41294140593948
        },
        {
            "x": 72.71479761105874,
            "y": 86.34307528923014,
            "z": 0.6347694961640649
        },
        {
            "x": 51.87354535359287,
            "y": 106.32018904732766,
            "z": -1.0
        },
        {
            "x": 69.09660573452472,
            "y": 84.23281333274693,
            "z": -0.6940880566695276
        },
        {
            "x": 62.45621942890269,
            "y": 109.63445057119607,
            "z": -1.0
        },
        {
            "x": 95.2514542350703,
            "y": 13.739746850238973,
            "z": 15.419247307189337
        },
        {
            "x": 69.63172866189232,
            "y": 105.92642446216841,
            "z": -1.0
        },
        {
            "x": 56.09225856172066,
            "y": 92.35318537305912,
            "z": -1.0
        },
        {
            "x": 90.2421440738616,
            "y": 95.06042221198216,
            "z": 32.9129248360649
        },
        {
            "x": 84.51635999360437,
            "y": 87.68425994251535,
            "z": 14.967349403149951
        },
        {
            "x": 94.85342621457522,
            "y": 71.68306798465386,
            "z": 41.44413162963747
        },
        {
            "x": 30.894253534125653,
            "y": 57.63632677390709,
            "z": -1.0
        },
        {
            "x": 91.74031847835334,
            "y": 58.52439667665384,
            "z": 52.02601530144239
        },
        {
            "x": 58.331281461467256,
            "y": 95.89649583738326,
            "z": -1.0
        },
        {
            "x": 23.796123254689192,
            "y": 63.372677055632046,
            "z": -1.0
        },
        {
            "x": 57.27979852917881,
            "y": 90.54691306248597,
            "z": -1.0
        },
        {
            "x": 36.68848858610345,
            "y": 76.04222699252833,
            "z": -1.0
        },
        {
            "x": 43.146188619827264,
            "y": 100.00178299933717,
            "z": -1.0
        },
        {
            "x": 48.559827206842755,
            "y": 93.48913882289501,
            "z": -1.0
        },
        {
            "x": 92.62498729633677,
            "y": 83.59125437308799,
            "z": 47.530405995291375
        },
        {
            "x": 42.66730215625852,
            "y": 71.50919488188184,
            "z": -1.0
        },
        {
            "x": 83.35272102774739,
            "y": 24.459597003119,
            "z": 10.851097624569706
        },
        {
            "x": 66.6452551281337,
            "y": 91.1074958606679,
            "z": -1.0
        },
        {
            "x": 76.67460839876976,
            "y": 101.99044832303477,
            "z": 7.596814358817793
        },
        {
            "x": 55.27591751794391,
            "y": 7.169608154974185,
            "z": -1.0
        },
        {
            "x": 98.56825347081309,
            "y": 22.002394398478472,
            "z": 34.40150817013318
        },
        {
            "x": 58.56154545904993,
            "y": 109.13965501509925,
            "z": -1.0
        },
        {
            "x": 98.95759119537088,
            "y": 67.52538090906033,
            "z": 56.59132597345267
        },
        {
            "x": 85.3254623474146,
            "y": 86.73278846959501,
            "z": 24.88570207111614
        },
        {
            "x": 64.56105703124742,
            "y": 19.696371789783413,
            "z": -1.0
        },
        {
            "x": 37.252899459905365,
            "y": 26.652513638725594,
            "z": -1.0
        },
        {
            "x": 102.5818282613299,
            "y": 38.13868883225157,
            "z": 48.64286985598549
        },
        {
            "x": 33.75377713906853,
            "y": 78.21856470866422,
            "z": -1.0
        },
        {
            "x": 89.28511537566946,
            "y": 18.59547001826033,
            "z": 11.15223415757192
        },
        {
            "x": 94.44984814922482,
            "y": 86.6727620266899,
            "z": 46.24079682189844
        },
        {
            "x": 93.45630304101823,
            "y": 97.49553276377956,
            "z": 38.91254085561923
        },
        {
            "x": 71.15096868200918,
            "y": 92.3513890385219,
            "z": 2.7249646767400035
        },
        {
            "x": 48.88122311816792,
            "y": 102.47431978205398,
            "z": -1.0
        },
        {
            "x": 85.93317968151129,
            "y": 97.97572441747727,
            "z": 23.38275763166439
        },
        {
            "x": 37.41370585860779,
            "y": 96.86733384364123,
            "z": -1.0
        },
        {
            "x": 92.40548586375208,
            "y": 70.45081095242058,
            "z": 38.08264843873408
        },
        {
            "x": 93.17233956244576,
            "y": 43.51414527539158,
            "z": 37.080639608190815
        },
        {
            "x": 26.79099512815303,
            "y": 73.8476147428378,
            "z": -1.0
        },
        {
            "x": 35.47725258268545,
            "y": 44.131596728867976,
            "z": -1.0
        },
        {
            "x": 51.429547908722746,
            "y": 93.57500499097306,
            "z": -1.0
        },
        {
            "x": 28.82841006453033,
            "y": 40.313153598807524,
            "z": -1.0
        },
        {
            "x": 41.055789954152644,
            "y": 98.9087239741887,
            "z": -1.0
        },
        {
            "x": 26.740198068967686,
            "y": 83.57554937531222,
            "z": -1.0
        },
        {
            "x": 87.08251998350111,
            "y": 77.99083527465126,
            "z": 27.045115040050522
        },
        {
            "x": 94.2865961720438,
            "y": 83.28986488306816,
            "z": 49.73150998724312
        },
        {
            "x": 78.92141425713706,
            "y": 104.91488323293365,
            "z": 7.973297751688367
        },
        {
            "x": 47.756792384571966,
            "y": 79.45271095771669,
            "z": -1.0
        },
        {
            "x": 69.38544932255962,
            "y": 104.2692322881107,
            "z": -1.0
        },
        {
            "x": 33.546222267136756,
            "y": 71.96845667332113,
            "z": -1.0
        },
        {
            "x": 79.98554550293407,
            "y": 26.706315701921326,
            "z": 10.022871636564169
        },
        {
            "x": 80.13383179227031,
            "y": 10.192659709352625,
            "z": 7.948530002627951
        },
        {
            "x": 52.709478586872685,
            "y": 104.54369179185065,
            "z": -1.0
        },
        {
            "x": 49.85156015364278,
            "y": 79.44422334415745,
            "z": -1.0
        },
        {
            "x": 87.8665683849606,
            "y": 78.73653014088168,
            "z": 30.229688420238922
        },
        {
            "x": 94.02056658861817,
            "y": 49.5773757178649,
            "z": 47.194134334614496
        },
        {
            "x": 78.49517180348685,
            "y": 106.8504822343221,
            "z": 6.558578799291947
        },
        {
            "x": 95.47318379206862,
            "y": 41.31627736228716,
            "z": 41.097526096130856
        }
    ],
    "center": {
        "x": 70.74978544947841,
        "y": 55.28134956004911,
        "z": 7.335642970432506
    },
    "radius": 30
}